{
    "type": "create:mixing",
    "ingredients": [{
        "tag": "forge:honeycombs/osmium"
    }],
    "results": [
        {
            "item": "mekanism:ingot_osmium",
            "chance": 0.90
        },
        {
            "fluid": "productivebees:honey",
            "amount": 50
        }
    ],
    "heatRequirement": "heated",
    "conditions": [
        {
            "type": "forge:mod_loaded",
            "modid": "create"
        },
        {
            "type": "forge:mod_loaded",
            "modid": "mekanism"
        }
    ]
}