{
  "type": "productivebees:centrifuge",
  "ingredient": {
    "type": "productivebees:component",
    "components": {
      "productivebees:bee_type": "productivebees:soularium"
    },
    "items": "productivebees:configurable_honeycomb"
  },
  "outputs": [
    {
      "item": {
        "item": "enderio:soularium_nugget"
      },
      "min": 5,
      "max": 5
    },
    {
      "item": {
        "item": "productivebees:wax"
      }
    }
  ],
  "neoforge:conditions": [
    {
      "type": "neoforge:mod_loaded",
      "modid": "enderio"
    },
    {
      "type": "productivebees:bee_exists",
      "bee": "productivebees:soularium"
    }
  ]
}