{
  "type": "productivebees:advanced_beehive",
  "ingredient": "productivebees:prismarine",
  "results": [
    {
      "item": {
        "type": "forge:nbt",
        "item": "productivebees:configurable_honeycomb",
        "nbt": {
          "EntityTag": {
            "type": "productivebees:prismarine"
          }
        }
      }
    },
    {
      "item": {
        "item": "minecraft:nautilus_shell"
      },
      "chance": 1
    }
  ],
  "conditions": [
    {
      "type": "productivebees:bee_exists",
      "bee": "productivebees:prismarine"
    }
  ]
}