{
    "name": "Lapis Bee",
    "icon": "minecraft:lapis_lazuli",
    "read_by_default": true,
    "category": "productivebees:hive",
    "flag": "productivebees:lapis",
    "pages": [
        {
            "type": "text",
            "title": "Lapis Bee",
            "text": "Bred from a $(l:bees/hive/redstone)Redstone Bee$(/l) and a $(l:bees/solitary/blue_banded)Blue Banded Bee$(/l).",
            "anchor": "lapis"
        },
        {
            "type": "entity",
            "entity": "productivebees:configurable_bee{type:'productivebees:lapis'}"
        }
    ]
}