{
  "type": "minecraft:entity",
  "pools": [
    {
      "rolls": 1,
      "entries": [
        {
          "type": "minecraft:alternatives",
          "children": [
            {
              "type": "minecraft:item",
              "functions": [
                {
                  "function": "productivebees:productivity"
                },
                {
                  "function": "productivebees:convert_to_comb",
                  "itemName": "minecraft:ender_pearl"
                }
              ],
              "conditions": [
                {
                  "condition": "productivebees:entity_is_productive_bee"
                },
                {
                  "condition": "productivebees:mod_loaded",
                  "modId": "beesourceful"
                }
              ],
              "name": "minecraft:ender_pearl"
            },
            {
              "type": "minecraft:item",
              "functions": [
                {
                  "function": "productivebees:productivity"
                }
              ],
              "conditions": [
                {
                  "condition": "productivebees:entity_is_productive_bee"
                }
              ],
              "name": "minecraft:ender_pearl"
            }
          ]
        }
      ]
    }
  ]
}